jsa_auth_middleware/__init__.py
jsa_auth_middleware/query_response.py
jsa_auth_middleware-0.0.3.4.dist-info/LICENSE
jsa_auth_middleware-0.0.3.4.dist-info/METADATA
jsa_auth_middleware-0.0.3.4.dist-info/WHEEL
jsa_auth_middleware-0.0.3.4.dist-info/top_level.txt
jsa_auth_middleware-0.0.3.4.dist-info/RECORD
