Metadata-Version: 2.1
Name: jsa-auth-middleware
Version: 0.0.3.4
Summary: JetStream Authentication MiddleWare
Home-page: https://github.com/JetstreamAfrica/jsa_sdks/tree/master/jsa_auth_middleware
Author: Kunsam002 :: Olukunle Ogunmokun
Author-email: kunsam002@gmail.com
License: MIT License
Platform: UNKNOWN
Classifier: Framework :: Django
Classifier: Framework :: Django :: 2.2
Classifier: Environment :: Web Environment
Classifier: Intended Audience :: Developers
Classifier: License :: OSI Approved :: MIT License
Classifier: Operating System :: OS Independent
Classifier: Programming Language :: Python :: 3 :: Only
Classifier: Programming Language :: Python :: 3.6
Classifier: Topic :: Software Development :: Libraries :: Application Frameworks
Classifier: Topic :: Software Development :: Libraries :: Python Modules
Requires-Python: >=3.6
Requires-Dist: Django (>=2.2.8)
Requires-Dist: requests (>=2.22)
